pyunit_xor/__init__.py
pyunit_xor/password.py
pyunit_xor-2025.4.11.dist-info/METADATA
pyunit_xor-2025.4.11.dist-info/WHEEL
pyunit_xor-2025.4.11.dist-info/top_level.txt
pyunit_xor-2025.4.11.dist-info/zip-safe
pyunit_xor-2025.4.11.dist-info/RECORD
