Metadata-Version: 2.1
Name: pyunit-xor
Version: 2025.4.11
Summary: 一个简单的异或生成Token
Home-page: https://github.com/pyunits/pyunit-xor
Author: 张伟
Author-email: jtyoui@qq.com
License: MIT Licence
Platform: any
Classifier: Programming Language :: Python :: 3
Classifier: License :: OSI Approved :: MIT License
Classifier: Operating System :: OS Independent
